{
  "version": 8,
  "$schema": "https://cmake.org/cmake/help/latest/_downloads/3e2d73bff478d88a7de0de736ba5e361/schema.json",
  "configurePresets": [
    {
      "name": "debug",
      "displayName": "Debug",
      "generator": "Ninja",
      "binaryDir": "build/debug",
      "cacheVariables": {
        "CMAKE_BUILD_TYPE": "Debug"
      }
    },
    {
      "name": "release",
      "displayName": "Release",
      "generator": "Ninja",
      "binaryDir": "build/release",
      "cacheVariables": {
        "CMAKE_BUILD_TYPE": "Release"
      }
    },
    {
      "name": "profile",
      "displayName": "Profile",
      "generator": "Ninja",
      "binaryDir": "build/profile",
      "cacheVariables": {
        "CMAKE_BUILD_TYPE": "RelWithDebInfo"
      }
    }
  ],
  "buildPresets": [
    {
      "name": "app-debug",
      "displayName": "App Debug Build",
      "configurePreset": "debug",
      "configuration": "Debug",
      "targets": ["native"]
    },
    {
      "name": "app-profile",
      "displayName": "App Profile Build",
      "configurePreset": "profile",
      "configuration": "Profile",
      "targets": ["native"]
    },
    {
      "name": "app-release",
      "displayName": "App Release Build",
      "configurePreset": "release",
      "configuration": "Release",
      "targets": ["native"]
    },
    {
      "name": "tests-debug",
      "displayName": "Tests Debug Build",
      "configurePreset": "debug",
      "configuration": "Debug",
      "targets": ["tests"]
    }
  ]
}